TM1_bedrock_py/__init__.py
TM1_bedrock_py/bedrock.py
TM1_bedrock_py/context_metadata.py
TM1_bedrock_py/extractor.py
TM1_bedrock_py/input.py
TM1_bedrock_py/json_log_formatter.py
TM1_bedrock_py/loader.py
TM1_bedrock_py/logging.json
TM1_bedrock_py/transformer.py
TM1_bedrock_py/utility.py
TM1_bedrock_py/airflow_executor/__init__.py
TM1_bedrock_py/airflow_executor/async_executor.py
TM1_bedrock_py/airflow_executor/common.py
TM1_bedrock_py/dimension_builder/__init__.py
TM1_bedrock_py/dimension_builder/apply.py
TM1_bedrock_py/dimension_builder/exceptions.py
TM1_bedrock_py/dimension_builder/io.py
TM1_bedrock_py/dimension_builder/normalize.py
TM1_bedrock_py/dimension_builder/utility.py
TM1_bedrock_py/dimension_builder/validate.py
tm1_bedrock_py-1.2.dist-info/licenses/LICENSE
tm1_bedrock_py-1.2.dist-info/METADATA
tm1_bedrock_py-1.2.dist-info/WHEEL
tm1_bedrock_py-1.2.dist-info/top_level.txt
tm1_bedrock_py-1.2.dist-info/RECORD
