Metadata-Version: 2.4
Name: tm1_bedrock_py
Version: 1.2
Summary: A python module for TM1 Bedrock.
Home-page: 
Author: 
Author-email: Akos Andras Nagy <akos.nagy@knowledgeseed.ch>, Eszter Buris <eszter.buris@knowledgeseed.ch>, David Ullmann <david.ullmann@knowledgeseed.ch>, Zsolt Moravcsik <zsolt.moravcsik@knowledgeseed.ch>
Maintainer-email: Akos Andras Nagy <akos.nagy@knowledgeseed.ch>, Eszter Buris <eszter.buris@knowledgeseed.ch>, David Ullmann <david.ullmann@knowledgeseed.ch>, Zsolt Moravcsik <zsolt.moravcsik@knowledgeseed.ch>
License-Expression: Apache-2.0
Project-URL: Documentation, https://tm1-bedrock-py.readthedocs.io/en/latest/
Project-URL: Repository, https://github.com/KnowledgeSeed/tm1_bedrock_py
Project-URL: Issues, https://github.com/KnowledgeSeed/tm1_bedrock_py/issues
Project-URL: Changelog, https://github.com/KnowledgeSeed/tm1_bedrock_py/CHANGELOG.md
Keywords: TM1,IBM Cognos TM1,Planning Analytics,PA,Cognos
Classifier: Programming Language :: Python :: 3
Classifier: Operating System :: OS Independent
Requires-Python: >=3.9
License-File: LICENSE
Requires-Dist: TM1py<3.0,>=2.1
Requires-Dist: pandas<3.0.0,>=2.3.3
Requires-Dist: json_logging<2.0.0,>=1.3.0
Requires-Dist: sqlalchemy<3.0.0,>=2.0.0
Requires-Dist: pyodbc<6.0.0,>=5.2.0
Requires-Dist: pyyaml<7.0,>=6.0
Requires-Dist: openpyxl>=3.1.0
Provides-Extra: airflow
Requires-Dist: apache-airflow<=2.11.0,>=2.4.0; python_version < "3.13" and extra == "airflow"
Requires-Dist: airflow_provider_tm1>=0.5.1; python_version < "3.13" and extra == "airflow"
Requires-Dist: jinja2<3.2.0,>=3.1.2; python_version < "3.13" and extra == "airflow"
Provides-Extra: postgres
Requires-Dist: apache-airflow-providers-postgres<7.0.0,>=3.3.0; python_version < "3.13" and extra == "postgres"
Provides-Extra: microsoft-mssql
Requires-Dist: apache-airflow-providers-microsoft-mssql<7.0.0,>=3.3.0; python_version < "3.13" and extra == "microsoft-mssql"
Provides-Extra: dev
Requires-Dist: parametrize_from_file<1.0.0,>=0.20.0; extra == "dev"
Requires-Dist: pytest<9.0.0,>=8.3.4; extra == "dev"
Requires-Dist: build<2.0.0,>=1.2.2.post1; extra == "dev"
Requires-Dist: matplotlib<4.0.0,>=3.7.0; extra == "dev"
Dynamic: license-file
Dynamic: requires-python
